LICENSE
README.md
setup.py
rawana/__init__.py
rawana/powers.py
rawana/stories.py
rawana.egg-info/PKG-INFO
rawana.egg-info/SOURCES.txt
rawana.egg-info/dependency_links.txt
rawana.egg-info/top_level.txt