Metadata-Version: 2.1
Name: rawana
Version: 0.1.1
Summary: A package about Rawana's super powers and stories
Home-page: https://github.com/ishanoshada/rawana
Author: Ishan Oshada
Author-email: ishan.kodithuwakku.offical@gmail.com
Classifier: Programming Language :: Python :: 3
Classifier: License :: OSI Approved :: MIT License
Classifier: Operating System :: OS Independent
License-File: LICENSE
